heatmappy/__init__.py
heatmappy/heatmap.py
heatmappy/video.py
heatmappy/assets/450pxdot.png
heatmappy/assets/SampleVideo_720x480_1mb.mp4
heatmappy/assets/cat.jpg
heatmappy/assets/default.png
heatmappy/assets/reveal.png
vnpt_heatmappy-0.2.7.dist-info/LICENSE
vnpt_heatmappy-0.2.7.dist-info/METADATA
vnpt_heatmappy-0.2.7.dist-info/WHEEL
vnpt_heatmappy-0.2.7.dist-info/top_level.txt
vnpt_heatmappy-0.2.7.dist-info/RECORD
