Metadata-Version: 2.1
Name: vnpt-heatmappy
Version: 0.2.7
Summary: Draw image heatmaps in python
Home-page: https://github.com/LumenResearch/heatmappy
Download-URL: https://github.com/LumenResearch/heatmappy/tarball/0.1.1
Author: Lumen Research
Author-email: development@lumen-research.com
Keywords: image,heatmap,heat map
Classifier: Programming Language :: Python :: 3
License-File: LICENSE
Requires-Dist: numpy>=1.17.3
Requires-Dist: matplotlib>=1.5.0
Requires-Dist: moviepy==1.0.3
Requires-Dist: Pillow<9.0.0,>=6.2.0
Requires-Dist: pyparsing>=2.0.6
Requires-Dist: python-dateutil>=2.4.2
Requires-Dist: pytz>=2015.7
Requires-Dist: six==1.16.0
Requires-Dist: wheel==0.24.0
